Workbook

Sheet 도서목록
A1: 도서ID | B1: 등록번호 | C1: 서명 | D1: 저자 | E1: 청구기호 | F1: 소장위치 | G1: 가격 | H1: 출판년도 | I1: 도서상세URL | J1: ISBN13 | K1: 카테고리 | L1: 상태 | M1: 신청가능수량 | N1: 신청중수량 | O1: 확정수량 | P1: 비고 | Q1: 원본번호
A2: BOOK-00001 | B2: E1433939 | C2: 4차 산업시대의 인성과 진로 및 취업 | D2: 김순향 | E2: 337.268 김56인3 | F2: 취업지원실(승학) | G2: 22800 | H2: 2022 | I2: https://library.donga.ac.kr/resource/library-catalog/?app=mirtech&mod=detail&record_id=936107 | K2: 진로/취업전략 | L2: =IF($M2<=($N2+$O2),"마감","신청가능") | M2: 1 | N2: =COUNTIFS(신청현황!$J:$J,$A2,신청현황!$C:$C,"신청접수")+COUNTIFS(신청현황!$J:$J,$A2,신청현황!$C:$C,"처리중") | O2: =COUNTIFS(신청현황!$J:$J,$A2,신청현황!$C:$C,"확정") | Q2: 1
A3: BOOK-00002 | B3: E1433952 | C3: (NCS기반) 진로탐색 및 취업과 창업 | D3: 김진욱 | E3: 325.33 김78진4 | F3: 취업지원실(승학) | G3: 23000 | H3: 2022 | I3: https://library.donga.ac.kr/resource/library-catalog/?app=mirtech&mod=detail&record_id=936131 | K3: NCS/인적성 | L3: =IF($M3<=($N3+$O3),"마감","신청가능") | M3: 1 | N3: =COUNTIFS(신청현황!$J:$J,$A3,신청현황!$C:$C,"신청접수")+COUNTIFS(신청현황!$J:$J,$A3,신청현황!$C:$C,"처리중") | O3: =COUNTIFS(신청현황!$J:$J,$A3,신청현황!$C:$C,"확정") | Q3: 2
A4: BOOK-00003 | B4: E1433984 | C4: 누가 봐도 뽑고 싶은 이공계 자소서 | D4: 취업지킴이 | E4: 325.337 취64누 | F4: 취업지원실(승학) | G4: 16000 | H4: 2022 | I4: https://library.donga.ac.kr/resource/library-catalog/?app=mirtech&mod=detail&record_id=936180 | K4: 자기소개서/이력서 | L4: =IF($M4<=($N4+$O4),"마감","신청가능") | M4: 1 | N4: =COUNTIFS(신청현황!$J:$J,$A4,신청현황!$C:$C,"신청접수")+COUNTIFS(신청현황!$J:$J,$A4,신청현황!$C:$C,"처리중") | O4: =COUNTIFS(신청현황!$J:$J,$A4,신청현황!$C:$C,"확정") | Q4: 3
A5: BOOK-00004 | B5: E1434165 | C5: 잡 블레스 유 | D5: 서창호 | E5: 325.33 서82잡 | F5: 취업지원실(승학) | G5: 15000 | H5: 2022 | I5: https://library.donga.ac.kr/resource/library-catalog/?app=mirtech&mod=detail&record_id=936215 | K5: 창업/경영경제 | L5: =IF($M5<=($N5+$O5),"마감","신청가능") | M5: 1 | N5: =COUNTIFS(신청현황!$J:$J,$A5,신청현황!$C:$C,"신청접수")+COUNTIFS(신청현황!$J:$J,$A5,신청현황!$C:$C,"처리중") | O5: =COUNTIFS(신청현황!$J:$J,$A5,신청현황!$C:$C,"확정") | Q5: 4
A6: BOOK-00005 | B6: E1400274 | C6: CAT+CJAT CJ그룹 종합적성검사 | D6: 취업적성연구소 | E6: 325.337 취64시6 =2 | F6: 취업지원실(승학) | G6: 19000 | H6: 2022 | I6: https://library.donga.ac.kr/resource/library-catalog/?app=mirtech&mod=detail&record_id=909800 | K6: NCS/인적성 | L6: =IF($M6<=($N6+$O6),"마감","신청가능") | M6: 1 | N6: =COUNTIFS(신청현황!$J:$J,$A6,신청현황!$C:$C,"신청접수")+COUNTIFS(신청현황!$J:$J,$A6,신청현황!$C:$C,"처리중") | O6: =COUNTIFS(신청현황!$J:$J,$A6,신청현황!$C:$C,"확정") | Q6: 5
A7: BOOK-00006 | B7: E1400412 | C7: AI 역량평가 & 스피치 솔루션 :합격자, 개발자, 채용 담당자가 말하는 AI 면접 스킬 | D7: 우설리 | E7: 325.337 우54에 | F7: 취업지원실(승학) | G7: 15000 | H7: 2022 | I7: https://library.donga.ac.kr/resource/library-catalog/?app=mirtech&mod=detail&record_id=910109 | K7: 면접/스피치 | L7: =IF($M7<=($N7+$O7),"마감","신청가능") | M7: 1 | N7: =COUNTIFS(신청현황!$J:$J,$A7,신청현황!$C:$C,"신청접수")+COUNTIFS(신청현황!$J:$J,$A7,신청현황!$C:$C,"처리중") | O7: =COUNTIFS(신청현황!$J:$J,$A7,신청현황!$C:$C,"확정") | Q7: 6
A8: BOOK-00007 | B8: E1400443 | C8: (더빅스쿨 공기업·금융권) 경영학 스파르타 300제 :10일 단/기/완/성 | D8: 더빅스쿨 인적성 연구소 | E8: 325.337 더48경 =2 | F8: 취업지원실(승학) | G8: 17000 | H8: 2022 | I8: https://library.donga.ac.kr/resource/library-catalog/?app=mirtech&mod=detail&record_id=909844 | K8: 공무원/자격시험 | L8: =IF($M8<=($N8+$O8),"마감","신청가능") | M8: 1 | N8: =COUNTIFS(신청현황!$J:$J,$A8,신청현황!$C:$C,"신청접수")+COUNTIFS(신청현황!$J:$J,$A8,신청현황!$C:$C,"처리중") | O8: =COUNTIFS(신청현황!$J:$J,$A8,신청현황!$C:$C,"확정") | Q8: 7
A9: BOOK-00008 | B9: E1400445 | C9: (더빅스쿨 공기업·금융권) 경제학 스파르타 300제 /10일 단/기/완/성 | D9: 더빅스쿨 인적성 연구소 | E9: 325.337 더48경ㅈ =2 | F9: 취업지원실(승학) | G9: 17000 | H9: 2022 | I9: https://library.donga.ac.kr/resource/library-catalog/?app=mirtech&mod=detail&record_id=909845 | K9: 공무원/자격시험 | L9: =IF($M9<=($N9+$O9),"마감","신청가능") | M9: 1 | N9: =COUNTIFS(신청현황!$J:$J,$A9,신청현황!$C:$C,"신청접수")+COUNTIFS(신청현황!$J:$J,$A9,신청현황!$C:$C,"처리중") | O9: =COUNTIFS(신청현황!$J:$J,$A9,신청현황!$C:$C,"확정") | Q9: 8
A10: BOOK-00009 | B10: E1400455 | C10: 공기업 객관식 경영학 기출 :500제 | D10: 혼JOB취업연구소 | E10: 325.077 혼72공 v.1 =2 | F10: 취업지원실(승학) | G10: 25000 | H10: 2022 | I10: https://library.donga.ac.kr/resource/library-catalog/?app=mirtech&mod=detail&record_id=910034 | K10: 공무원/자격시험 | L10: =IF($M10<=($N10+$O10),"마감","신청가능") | M10: 1 | N10: =COUNTIFS(신청현황!$J:$J,$A10,신청현황!$C:$C,"신청접수")+COUNTIFS(신청현황!$J:$J,$A10,신청현황!$C:$C,"처리중") | O10: =COUNTIFS(신청현황!$J:$J,$A10,신청현황!$C:$C,"확정") | Q10: 9
A11: BOOK-00010 | B11: E1400486 | C11: 슬기로운 무역 취업 | D11: 이기찬 | E11: 326.23 이18슬 | F11: 취업지원실(승학) | G11: 16500 | H11: 2022 | I11: https://library.donga.ac.kr/resource/library-catalog/?app=mirtech&mod=detail&record_id=910074 | K11: 진로/취업전략 | L11: =IF($M11<=($N11+$O11),"마감","신청가능") | M11: 1 | N11: =COUNTIFS(신청현황!$J:$J,$A11,신청현황!$C:$C,"신청접수")+COUNTIFS(신청현황!$J:$J,$A11,신청현황!$C:$C,"처리중") | O11: =COUNTIFS(신청현황!$J:$J,$A11,신청현황!$C:$C,"확정") | Q11: 10
A12: BOOK-00011 | B12: E1400490 | C12: (알고 보면 너무 쉬운) 공무원/공기업 면접 공식 | D12: 이혜정 | E12: 351.133 이94공 =2 | F12: 취업지원실(승학) | G12: 16000 | H12: 2022 | I12: https://library.donga.ac.kr/resource/library-catalog/?app=mirtech&mod=detail&record_id=910076 | K12: 면접/스피치 | L12: =IF($M12<=($N12+$O12),"마감","신청가능") | M12: 1 | N12: =COUNTIFS(신청현황!$J:$J,$A12,신청현황!$C:$C,"신청접수")+COUNTIFS(신청현황!$J:$J,$A12,신청현황!$C:$C,"처리중") | O12: =COUNTIFS(신청현황!$J:$J,$A12,신청현황!$C:$C,"확정") | Q12: 11
A13: BOOK-00012 | B13: E1400495 | C13: (에듀윌 공기업) 실제 면접관이 말하는 NCS 자소서와 면접 :인문·상경계 | D13: 윤성훈 | E13: 325.337 윤54실 =2 | F13: 취업지원실(승학) | G13: 17000 | H13: 2022 | I13: https://library.donga.ac.kr/resource/library-catalog/?app=mirtech&mod=detail&record_id=910080 | K13: 면접/스피치 | L13: =IF($M13<=($N13+$O13),"마감","신청가능") | M13: 1 | N13: =COUNTIFS(신청현황!$J:$J,$A13,신청현황!$C:$C,"신청접수")+COUNTIFS(신청현황!$J:$J,$A13,신청현황!$C:$C,"처리중") | O13: =COUNTIFS(신청현황!$J:$J,$A13,신청현황!$C:$C,"확정") | Q13: 12
... A4073: BOOK-04072 | B4073: E0560631 | C4073: (2012) 삼성그룹직무적성검사:New SSAT.[2],이공계 | D4073: 한국고시회 | E4073: 325.337 한16삼 v.2012:2 =2 | F4073: 취업지원실(승학) | G4073: 0 | H4073: 2010 | I4073: https://library.donga.ac.kr/resource/library-catalog/?app=mirtech&mod=detail&record_id=694963 | K4073: NCS/인적성 | L4073: =IF($M4073<=($N4073+$O4073),"마감","신청가능") | M4073: 1 | N4073: =COUNTIFS(신청현황!$J:$J,$A4073,신청현황!$C:$C,"신청접수")+COUNTIFS(신청현황!$J:$J,$A4073,신청현황!$C:$C,"처리중") | O4073: =COUNTIFS(신청현황!$J:$J,$A4073,신청현황!$C:$C,"확정") | Q4073: 4072
A4074: BOOK-04073 | B4074: E0560639 | C4074: (삼성그룹) SSAT 기출문제집.[2],이공계 | E4074: 325.337 한16S4 v.2 | F4074: 취업지원실(승학) | G4074: 24000 | H4074: 2010 | I4074: https://library.donga.ac.kr/resource/library-catalog/?app=mirtech&mod=detail&record_id=705883 | K4074: NCS/인적성 | L4074: =IF($M4074<=($N4074+$O4074),"마감","신청가능") | M4074: 1 | N4074: =COUNTIFS(신청현황!$J:$J,$A4074,신청현황!$C:$C,"신청접수")+COUNTIFS(신청현황!$J:$J,$A4074,신청현황!$C:$C,"처리중") | O4074: =COUNTIFS(신청현황!$J:$J,$A4074,신청현황!$C:$C,"확정") | Q4074: 4073
A4075: BOOK-04074 | B4075: E0560641 | C4075: (삼성그룹) SSAT 기출문제집.[1],인문계 | E4075: 325.337 한16S4 v.1 | F4075: 취업지원실(승학) | G4075: 22000 | H4075: 2010 | I4075: https://library.donga.ac.kr/resource/library-catalog/?app=mirtech&mod=detail&record_id=705882 | K4075: NCS/인적성 | L4075: =IF($M4075<=($N4075+$O4075),"마감","신청가능") | M4075: 1 | N4075: =COUNTIFS(신청현황!$J:$J,$A4075,신청현황!$C:$C,"신청접수")+COUNTIFS(신청현황!$J:$J,$A4075,신청현황!$C:$C,"처리중") | O4075: =COUNTIFS(신청현황!$J:$J,$A4075,신청현황!$C:$C,"확정") | Q4075: 4074
A4076: BOOK-04075 | B4076: E0560644 | C4076: (2012)삼성그룹 직무적성검사 일반상식.[2],이공계 | D4076: 한국고시회 | E4076: 325.337 한16삼ㄱ v.2012;2 =2 | F4076: 취업지원실(승학) | G4076: 22000 | H4076: 2010 | I4076: https://library.donga.ac.kr/resource/library-catalog/?app=mirtech&mod=detail&record_id=705755 | K4076: NCS/인적성 | L4076: =IF($M4076<=($N4076+$O4076),"마감","신청가능") | M4076: 1 | N4076: =COUNTIFS(신청현황!$J:$J,$A4076,신청현황!$C:$C,"신청접수")+COUNTIFS(신청현황!$J:$J,$A4076,신청현황!$C:$C,"처리중") | O4076: =COUNTIFS(신청현황!$J:$J,$A4076,신청현황!$C:$C,"확정") | Q4076: 4075
A4077: BOOK-04076 | B4077: E0560645 | C4077: (서박사) 공사ㆍ공단 일반 상식 | D4077: 서영학 | E4077: 001.76 서64공 v.2013 | F4077: 취업지원실(승학) | G4077: 27000 | H4077: 2010 | I4077: https://library.donga.ac.kr/resource/library-catalog/?app=mirtech&mod=detail&record_id=705751 | K4077: 컴퓨터/데이터 | L4077: =IF($M4077<=($N4077+$O4077),"마감","신청가능") | M4077: 1 | N4077: =COUNTIFS(신청현황!$J:$J,$A4077,신청현황!$C:$C,"신청접수")+COUNTIFS(신청현황!$J:$J,$A4077,신청현황!$C:$C,"처리중") | O4077: =COUNTIFS(신청현황!$J:$J,$A4077,신청현황!$C:$C,"확정") | Q4077: 4076
A4078: BOOK-04077 | B4078: E0560646 | C4078: (서박사) 공사ㆍ공단 일반 상식 | D4078: 서영학 | E4078: 001.76 서64공 v.2013 =2 | F4078: 취업지원실(승학) | G4078: 27000 | H4078: 2010 | I4078: https://library.donga.ac.kr/resource/library-catalog/?app=mirtech&mod=detail&record_id=705751 | K4078: 컴퓨터/데이터 | L4078: =IF($M4078<=($N4078+$O4078),"마감","신청가능") | M4078: 1 | N4078: =COUNTIFS(신청현황!$J:$J,$A4078,신청현황!$C:$C,"신청접수")+COUNTIFS(신청현황!$J:$J,$A4078,신청현황!$C:$C,"처리중") | O4078: =COUNTIFS(신청현황!$J:$J,$A4078,신청현황!$C:$C,"확정") | Q4078: 4077
A4079: BOOK-04078 | B4079: E0560648 | C4079: (2011 시나공) 일반상식의 재구성 | D4079: 길벗알앤디.일반상식연구팀. | E4079: 031 길44일 | F4079: 취업지원실(승학) | G4079: 26000 | H4079: 2010 | I4079: https://library.donga.ac.kr/resource/library-catalog/?app=mirtech&mod=detail&record_id=705746 | K4079: 컴퓨터/데이터 | L4079: =IF($M4079<=($N4079+$O4079),"마감","신청가능") | M4079: 1 | N4079: =COUNTIFS(신청현황!$J:$J,$A4079,신청현황!$C:$C,"신청접수")+COUNTIFS(신청현황!$J:$J,$A4079,신청현황!$C:$C,"처리중") | O4079: =COUNTIFS(신청현황!$J:$J,$A4079,신청현황!$C:$C,"확정") | Q4079: 4078
A4080: BOOK-04079 | B4080: E0560654 | C4080: 웅진그룹 직무적합도검사 =Aptitude test :웅진 직무적합도검사 완벽대비 | D4080: 적성검사연구소 | E4080: 325.337 적54웅 | F4080: 취업지원실(승학) | G4080: 17000 | H4080: 2010 | I4080: https://library.donga.ac.kr/resource/library-catalog/?app=mirtech&mod=detail&record_id=705738 | K4080: 직무/실무역량 | L4080: =IF($M4080<=($N4080+$O4080),"마감","신청가능") | M4080: 1 | N4080: =COUNTIFS(신청현황!$J:$J,$A4080,신청현황!$C:$C,"신청접수")+COUNTIFS(신청현황!$J:$J,$A4080,신청현황!$C:$C,"처리중") | O4080: =COUNTIFS(신청현황!$J:$J,$A4080,신청현황!$C:$C,"확정") | Q4080: 4079
A4081: BOOK-04080 | B4081: E0560655 | C4081: 웅진그룹 직무적합도검사 =Aptitude test :웅진 직무적합도검사 완벽대비 | D4081: 적성검사연구소 | E4081: 325.337 적54웅 =2 | F4081: 취업지원실(승학) | G4081: 17000 | H4081: 2010 | I4081: https://library.donga.ac.kr/resource/library-catalog/?app=mirtech&mod=detail&record_id=705738 | K4081: 직무/실무역량 | L4081: =IF($M4081<=($N4081+$O4081),"마감","신청가능") | M4081: 1 | N4081: =COUNTIFS(신청현황!$J:$J,$A4081,신청현황!$C:$C,"신청접수")+COUNTIFS(신청현황!$J:$J,$A4081,신청현황!$C:$C,"처리중") | O4081: =COUNTIFS(신청현황!$J:$J,$A4081,신청현황!$C:$C,"확정") | Q4081: 4080
A4082: BOOK-04081 | B4082: E0560660 | C4082: (2012+) 은행/증권/보험 직무적성(능력)검사 인성검사(인적성검사) | D4082: 한국고시회 | E4082: 325.337 한16은 v.2012 | F4082: 취업지원실(승학) | G4082: 25000 | H4082: 2010 | I4082: https://library.donga.ac.kr/resource/library-catalog/?app=mirtech&mod=detail&record_id=705831 | K4082: NCS/인적성 | L4082: =IF($M4082<=($N4082+$O4082),"마감","신청가능") | M4082: 1 | N4082: =COUNTIFS(신청현황!$J:$J,$A4082,신청현황!$C:$C,"신청접수")+COUNTIFS(신청현황!$J:$J,$A4082,신청현황!$C:$C,"처리중") | O4082: =COUNTIFS(신청현황!$J:$J,$A4082,신청현황!$C:$C,"확정") | Q4082: 4081
A4083: BOOK-04082 | B4083: E0560670 | C4083: (E·LAND)직무적성검사 :원칙을 지키는 신뢰받는 기업 | D4083: 적성검사연구소 | E4083: 325.337 적54직ㅇ v.2012 | F4083: 취업지원실(승학) | G4083: 17000 | H4083: 2010 | I4083: https://library.donga.ac.kr/resource/library-catalog/?app=mirtech&mod=detail&record_id=705816 | K4083: NCS/인적성 | L4083: =IF($M4083<=($N4083+$O4083),"마감","신청가능") | M4083: 1 | N4083: =COUNTIFS(신청현황!$J:$J,$A4083,신청현황!$C:$C,"신청접수")+COUNTIFS(신청현황!$J:$J,$A4083,신청현황!$C:$C,"처리중") | O4083: =COUNTIFS(신청현황!$J:$J,$A4083,신청현황!$C:$C,"확정") | Q4083: 4082
A4084: BOOK-04083 | B4084: E0560671 | C4084: (E·LAND)직무적성검사 :원칙을 지키는 신뢰받는 기업 | D4084: 적성검사연구소 | E4084: 325.337 적54직ㅇ v.2012 =2 | F4084: 취업지원실(승학) | G4084: 17000 | H4084: 2010 | I4084: https://library.donga.ac.kr/resource/library-catalog/?app=mirtech&mod=detail&record_id=705816 | K4084: NCS/인적성 | L4084: =IF($M4084<=($N4084+$O4084),"마감","신청가능") | M4084: 1 | N4084: =COUNTIFS(신청현황!$J:$J,$A4084,신청현황!$C:$C,"신청접수")+COUNTIFS(신청현황!$J:$J,$A4084,신청현황!$C:$C,"처리중") | O4084: =COUNTIFS(신청현황!$J:$J,$A4084,신청현황!$C:$C,"확정") | Q4084: 4083
A4085: BOOK-04084 | B4085: E0560681 | C4085: 직무적성검사 Pass 시사일반상식 | D4085: 한국고시회.편집부 | E4085: 031.076 한16직 | F4085: 취업지원실(승학) | G4085: 20000 | H4085: 2010 | I4085: https://library.donga.ac.kr/resource/library-catalog/?app=mirtech&mod=detail&record_id=705800 | K4085: NCS/인적성 | L4085: =IF($M4085<=($N4085+$O4085),"마감","신청가능") | M4085: 1 | N4085: =COUNTIFS(신청현황!$J:$J,$A4085,신청현황!$C:$C,"신청접수")+COUNTIFS(신청현황!$J:$J,$A4085,신청현황!$C:$C,"처리중") | O4085: =COUNTIFS(신청현황!$J:$J,$A4085,신청현황!$C:$C,"확정") | Q4085: 4084
A4086: BOOK-04085 | B4086: E0560705 | C4086: (한 권으로 끝내는) 직무적성검사 bible =Bible in aptitude test.[2012] :대기업 직무적성검사 종합본 | D4086: 타임적성검사연구소 | E4086: 325.337 타68직ㅁ2 | F4086: 취업지원실(승학) | G4086: 25000 | H4086: 2010 | I4086: https://library.donga.ac.kr/resource/library-catalog/?app=mirtech&mod=detail&record_id=705714 | K4086: NCS/인적성 | L4086: =IF($M4086<=($N4086+$O4086),"마감","신청가능") | M4086: 1 | N4086: =COUNTIFS(신청현황!$J:$J,$A4086,신청현황!$C:$C,"신청접수")+COUNTIFS(신청현황!$J:$J,$A4086,신청현황!$C:$C,"처리중") | O4086: =COUNTIFS(신청현황!$J:$J,$A4086,신청현황!$C:$C,"확정") | Q4086: 4085
A4087: BOOK-04086 | B4087: E0560709 | C4087: (2012+) 한화그룹 인적성검사 HAT.[1],인문계 | D4087: 한국고시회 | E4087: 325.337 한16한 v.2012:1 | F4087: 취업지원실(승학) | G4087: 16000 | H4087: 2010 | I4087: https://library.donga.ac.kr/resource/library-catalog/?app=mirtech&mod=detail&record_id=705732 | K4087: NCS/인적성 | L4087: =IF($M4087<=($N4087+$O4087),"마감","신청가능") | M4087: 1 | N4087: =COUNTIFS(신청현황!$J:$J,$A4087,신청현황!$C:$C,"신청접수")+COUNTIFS(신청현황!$J:$J,$A4087,신청현황!$C:$C,"처리중") | O4087: =COUNTIFS(신청현황!$J:$J,$A4087,신청현황!$C:$C,"확정") | Q4087: 4086
... A4727: BOOK-04726 | B4727: E1276346 | C4727: 새들도 세상을 뜨는구나 :황지우 시집 | D4727: 황지우 | E4727: 811.6 황79새2 | F4727: 취업지원실(승학) | G4727: 8000 | H4727: 1993 | I4727: https://library.donga.ac.kr/resource/library-catalog/?app=mirtech&mod=detail&record_id=769987 | K4727: 문학/교양 | L4727: =IF($M4727<=($N4727+$O4727),"마감","신청가능") | M4727: 1 | N4727: =COUNTIFS(신청현황!$J:$J,$A4727,신청현황!$C:$C,"신청접수")+COUNTIFS(신청현황!$J:$J,$A4727,신청현황!$C:$C,"처리중") | O4727: =COUNTIFS(신청현황!$J:$J,$A4727,신청현황!$C:$C,"확정") | Q4727: 4726

Sheet 신청현황
A1: 신청ID | B1: 신청일시 | C1: 상태 | D1: 학생명 | E1: 학번 | F1: 학과 | G1: 연락처 | H1: 이메일 | I1: 신청경로 | J1: 도서ID | K1: 등록번호 | L1: 서명 | M1: 저자 | N1: ISBN13 | O1: 메모 | P1: 처리자 | Q1: 처리일시

Sheet 이용자
A1: 학번 | B1: 성명 | C1: 휴대폰번호 | D1: 개인정보동의 | E1: 최초로그인 | F1: 최근로그인 | G1: 로그인횟수

Sheet 설정
A1: 설정항목 | B1: 값 | C1: 비고
A2: SPREADSHEET_ID | C2: 이 구글시트의 ID
A3: ALADIN_TTB_KEY | C3: 알라딘 TTBKey는 Apps Script 프로젝트 속성에 저장 권장
A4: EVENT_STATUS | C4: OPEN
A5: WEB_APP_URL | C5: Apps Script 배포 후 웹 앱 URL 입력
